LICENSE
README.md
pyproject.toml
setup.py
diffprivlib_logger/__init__.py
diffprivlib_logger/deserialise.py
diffprivlib_logger/serialise.py
diffprivlib_logger.egg-info/PKG-INFO
diffprivlib_logger.egg-info/SOURCES.txt
diffprivlib_logger.egg-info/dependency_links.txt
diffprivlib_logger.egg-info/requires.txt
diffprivlib_logger.egg-info/top_level.txt
tests/test_de_serialisation.py