Metadata-Version: 2.1
Name: diffprivlib_logger
Version: 0.0.1
Summary: A logger wrapper for DiffPrivLib
Home-page: https://github.com/dscc-admin/lomas/
Author: Data Science Competence Center, Swiss Federal Statistical Office
Author-email: dscc@bfs.admin.ch
License: MIT
Keywords: diffprivliv,logger,serialiser,deserialiser
Classifier: Development Status :: 3 - Alpha
Classifier: Intended Audience :: Developers
Classifier: License :: OSI Approved :: MIT License
Classifier: Programming Language :: Python :: 3.11
Requires-Python: >=3.10, <4
License-File: LICENSE
Requires-Dist: diffprivlib>=0.6.0
Requires-Dist: scikit-learn==1.5.0
